beaver_logs/__init__.py
beaver_logs/client.py
beaver_logs-0.1.23.dist-info/METADATA
beaver_logs-0.1.23.dist-info/WHEEL
beaver_logs-0.1.23.dist-info/licenses/LICENSE
beaver_logs-0.1.23.dist-info/RECORD
